yatlogger/__init__.py
yatlogger/__main__.py
yatlogger/config.py
yatlogger/register.py
yatlogger-0.1.3.dist-info/WHEEL
yatlogger-0.1.3.dist-info/METADATA
yatlogger-0.1.3.dist-info/RECORD
