Metadata-Version: 2.1
Name: yatlogger
Version: 0.1.3
Summary: Yet another telegram logger
Home-page: https://github.com/cyd3r/yatlogger
License: MIT
Keywords: logger,telegram,chat bot,notification,exception handler
Author: cyd3r
Author-email: cyd3rhacker@gmail.com
Requires-Python: >=3.6,<4.0
Classifier: Intended Audience :: Developers
Classifier: Intended Audience :: Science/Research
Classifier: License :: OSI Approved :: MIT License
Classifier: Operating System :: OS Independent
Classifier: Programming Language :: Python :: 3
Classifier: Programming Language :: Python :: 3.6
Classifier: Programming Language :: Python :: 3.7
Classifier: Programming Language :: Python :: 3.8
Classifier: Programming Language :: Python :: 3.9
Classifier: Topic :: Communications :: Chat
Classifier: Topic :: System :: Logging
Requires-Dist: python-telegram-bot (>=13.1,<14.0)
Project-URL: Repository, https://github.com/cyd3r/yatlogger
